bits/__init__.py
bits/helpers/__init__.py
bits_helpers-1.0.2.dist-info/METADATA
bits_helpers-1.0.2.dist-info/WHEEL
bits_helpers-1.0.2.dist-info/top_level.txt
bits_helpers-1.0.2.dist-info/RECORD
