Metadata-Version: 2.1
Name: bits-helpers
Version: 1.0.2
Summary: BITS Helpers
Home-page: UNKNOWN
Author: Lukas Karlsson
Author-email: karlsson@broadinstitute.org
License: Apache Software License
Platform: UNKNOWN
